qaf/__init__.py
qaf/listeners.py
qaf/automation/__init__.py
qaf/automation/bdd2/__init__.py
qaf/automation/bdd2/bdd_keywords.py
qaf/automation/bdd2/bddstep_executor.py
qaf/automation/bdd2/factory.py
qaf/automation/bdd2/model.py
qaf/automation/bdd2/parser.py
qaf/automation/bdd2/qaf_teststep.py
qaf/automation/bdd2/step_registry.py
qaf/automation/config/logging_config.ini
qaf/automation/core/__init__.py
qaf/automation/core/checkpoint_bean.py
qaf/automation/core/command_log_bean.py
qaf/automation/core/configurations_manager.py
qaf/automation/core/load_class.py
qaf/automation/core/message_type.py
qaf/automation/core/qaf_exceptions.py
qaf/automation/core/reporter.py
qaf/automation/core/singleton.py
qaf/automation/core/test_base.py
qaf/automation/integration/__init__.py
qaf/automation/integration/result_updator.py
qaf/automation/integration/testcase_result_updator.py
qaf/automation/integration/testcase_run_result.py
qaf/automation/keys/__init__.py
qaf/automation/keys/application_properties.py
qaf/automation/report/__init__.py
qaf/automation/report/json_reporter.py
qaf/automation/report/status_counter.py
qaf/automation/report/utils.py
qaf/automation/step_def/__init__.py
qaf/automation/step_def/common_steps.py
qaf/automation/step_def/ws_common_steps.py
qaf/automation/ui/__init__.py
qaf/automation/ui/js_toolkit.py
qaf/automation/ui/util/__init__.py
qaf/automation/ui/util/dynamic_wait.py
qaf/automation/ui/util/locator_util.py
qaf/automation/ui/util/qaf_element_expected_conditions.py
qaf/automation/ui/util/qaf_wd_expected_conditions.py
qaf/automation/ui/webdriver/__init__.py
qaf/automation/ui/webdriver/abstract_listener.py
qaf/automation/ui/webdriver/base_test_page.py
qaf/automation/ui/webdriver/command_tracker.py
qaf/automation/ui/webdriver/driver_factory.py
qaf/automation/ui/webdriver/options.py
qaf/automation/ui/webdriver/qaf_web_driver.py
qaf/automation/ui/webdriver/qaf_web_element.py
qaf/automation/ui/webdriver/qaf_webdriver_listener.py
qaf/automation/util/__init__.py
qaf_python-1.0.0b0.dist-info/LICENSE
qaf_python-1.0.0b0.dist-info/LICENSE.txt
qaf_python-1.0.0b0.dist-info/METADATA
qaf_python-1.0.0b0.dist-info/WHEEL
qaf_python-1.0.0b0.dist-info/entry_points.txt
qaf_python-1.0.0b0.dist-info/top_level.txt
qaf_python-1.0.0b0.dist-info/RECORD
