Metadata-Version: 2.1
Name: qaf-python
Version: 1.0.0b0
Summary: This is Automation framework for Python developed by Infostretch
Home-page: https://github.com/qmetry/qaf-python
Author: Nishith Shah, Chirag Jayswal
Author-email: nishith.shah@infostretch.com
Maintainer-email: nishith.shah@infostretch.com
License: MIT
Keywords: qaf,bdd,automation,python-selenium,python-automation,appium,python-appium
Classifier: Development Status :: 4 - Beta
Classifier: Intended Audience :: Developers
Classifier: Natural Language :: English
Classifier: Operating System :: OS Independent
Classifier: License :: OSI Approved :: MIT License
Classifier: Programming Language :: Python :: 3
Classifier: Topic :: Software Development :: Quality Assurance
Classifier: Topic :: Software Development :: Testing
Requires-Python: >=3.6
License-File: LICENSE
License-File: LICENSE.txt
Requires-Dist: selenium (~=4.9.1)
Requires-Dist: Appium-Python-Client (~=2.10.1)
Requires-Dist: behave (~=1.2.6)
Requires-Dist: PyHamcrest (~=1.9.0)
Requires-Dist: requests (~=2.31.0)
Requires-Dist: jmespath (~=1.0.0)
Requires-Dist: webdriver-manager (~=3.8.6)
Requires-Dist: simpleeval (==0.9.13)
Requires-Dist: pytest (~=7.3.1)
